[
  {
    "id": "cd7299a1-b41c-4553-8f80-114f4490a5c4",
    "timestamp": "2025-03-11T04:16:59.607Z",
    "type": "error_encountered",
    "level": "error",
    "summary": "ログディレクトリ構造のテスト - エラーログ",
    "details": {
      "errorType": "SystemConfigError",
      "message": "これはテスト用のエラーログです",
      "filePath": "test-file.ts",
      "lineNumber": 123
    },
    "intention": "新しいログディレクトリ構造でエラーログが適切に保存されるかの検証",
    "context": "ログディレクトリ構造を変更後、各ログレベルが適切なディレクトリに保存されるか確認するテスト"
  },
  {
    "id": "0d830fef-5ceb-4384-8472-c9c9ef34deec",
    "timestamp": "2025-03-11T08:38:53.041Z",
    "type": "error_encountered",
    "level": "warn",
    "summary": "internal/uiパッケージが未実装によるコンパイルエラー",
    "details": {
      "error": "could not import github.com/annenpolka/jikanicle/internal/ui (no required module provides package)",
      "file": "cmd/jikanicle/main.go",
      "line": 8,
      "context": "メインエントリーポイント実装中のインポートエラー"
    },
    "intention": "エラーを把握し、適切に対応するために記録",
    "context": "Goプロジェクトの初期化作業中、必要なパッケージが未実装"
  }
]